awpie.py
awpie-0.4.0.dist-info/METADATA
awpie-0.4.0.dist-info/WHEEL
awpie-0.4.0.dist-info/entry_points.txt
awpie-0.4.0.dist-info/licenses/LICENSE
awpie-0.4.0.dist-info/RECORD
