Metadata-Version: 2.1
Name: awpie
Version: 0.4.0
Summary: Using Python as awk alternative
Author-email: AN Long <aisk1988@gmail.com>
License: MIT License
License-File: LICENSE
Requires-Python: >=3.8
